ad_vision_01/__init__.py
ad_vision_01/camera.py
ad_vision_01/classifier.py
ad_vision_01/export.py
ad_vision_01/hubconf.py
ad_vision_01/label.py
ad_vision_01/objectdetection.py
ad_vision_01/posecalculator.py
ad_vision_01/models/__init__.py
ad_vision_01/models/common.py
ad_vision_01/models/experimental.py
ad_vision_01/models/tf.py
ad_vision_01/models/yolo.py
ad_vision_01/utils/__init__.py
ad_vision_01/utils/activations.py
ad_vision_01/utils/augmentations.py
ad_vision_01/utils/autoanchor.py
ad_vision_01/utils/autobatch.py
ad_vision_01/utils/callbacks.py
ad_vision_01/utils/dataloaders.py
ad_vision_01/utils/downloads.py
ad_vision_01/utils/general.py
ad_vision_01/utils/loss.py
ad_vision_01/utils/metrics.py
ad_vision_01/utils/plots.py
ad_vision_01/utils/torch_utils.py
ad_vision_01/utils/triton.py
ad_vision_01/utils/aws/__init__.py
ad_vision_01/utils/aws/resume.py
ad_vision_01/utils/flask_rest_api/example_request.py
ad_vision_01/utils/flask_rest_api/restapi.py
ad_vision_01/utils/loggers/__init__.py
ad_vision_01/utils/loggers/clearml/__init__.py
ad_vision_01/utils/loggers/clearml/clearml_utils.py
ad_vision_01/utils/loggers/clearml/hpo.py
ad_vision_01/utils/loggers/comet/__init__.py
ad_vision_01/utils/loggers/comet/comet_utils.py
ad_vision_01/utils/loggers/comet/hpo.py
ad_vision_01/utils/loggers/wandb/__init__.py
ad_vision_01/utils/loggers/wandb/log_dataset.py
ad_vision_01/utils/loggers/wandb/sweep.py
ad_vision_01/utils/loggers/wandb/wandb_utils.py
ad_vision_01/utils/segment/__init__.py
ad_vision_01/utils/segment/augmentations.py
ad_vision_01/utils/segment/dataloaders.py
ad_vision_01/utils/segment/general.py
ad_vision_01/utils/segment/loss.py
ad_vision_01/utils/segment/metrics.py
ad_vision_01/utils/segment/plots.py
ad_vision-0.0.3.dist-info/LICENSE
ad_vision-0.0.3.dist-info/METADATA
ad_vision-0.0.3.dist-info/WHEEL
ad_vision-0.0.3.dist-info/top_level.txt
ad_vision-0.0.3.dist-info/RECORD
